setup.py
lib10x/__init__.py
lib10x/lib10x.py
lib10x/sample.py
lib10x.egg-info/PKG-INFO
lib10x.egg-info/SOURCES.txt
lib10x.egg-info/dependency_links.txt
lib10x.egg-info/top_level.txt