Metadata-Version: 1.1
Name: lib10x
Version: 0.9.0
Summary: A library for analyzing 10X Genomics data.
Home-page: https://github.com/antonybholmes/lib10x
Author: Antony B Holmes
Author-email: antony.b.holmes@gmail.com
License: UNKNOWN
Platform: UNKNOWN
Classifier: Programming Language :: Python :: 3
Classifier: License :: OSI Approved :: MIT License
Classifier: Operating System :: OS Independent
